pyAOBS/__init__.py
pyAOBS/model_building/__init__.py
pyAOBS/model_building/models.py
pyAOBS/model_building/read.py
pyAOBS/model_building/test_zeltform.py
pyAOBS/model_building/zeltform.py
pyAOBS/processors/__init__.py
pyAOBS/processors/su_processor.py
pyAOBS/utils/__init__.py
pyAOBS/visualization/__init__.py
pyAOBS/visualization/show_model.py
pyAOBS/visualization/test_show_model.py
pyAOBS-0.1.1.dist-info/LICENSE
pyAOBS-0.1.1.dist-info/METADATA
pyAOBS-0.1.1.dist-info/WHEEL
pyAOBS-0.1.1.dist-info/top_level.txt
pyAOBS-0.1.1.dist-info/RECORD
