Metadata-Version: 2.2
Name: pyAOBS
Version: 0.1.1
Summary: A package for seismic data processing and visualization
Home-page: https://github.com/go223-pyAOBS/pyAOBS
Author: Haibo Huang
Author-email: go223@scsio.ac.cn
Project-URL: Bug Reports, https://github.com/go223-pyAOBS/pyAOBS/issues
Project-URL: Source, https://github.com/go223-pyAOBS/pyAOBS
Classifier: Development Status :: 3 - Alpha
Classifier: Intended Audience :: Science/Research
Classifier: Topic :: Scientific/Engineering :: Physics
Classifier: Programming Language :: Python :: 3
Classifier: Programming Language :: Python :: 3.7
Classifier: Programming Language :: Python :: 3.8
Classifier: Programming Language :: Python :: 3.9
Classifier: License :: OSI Approved :: MIT License
Classifier: Operating System :: OS Independent
Requires-Python: >=3.7
License-File: LICENSE
Requires-Dist: numpy>=1.20.0
Requires-Dist: xarray>=0.16.0
Requires-Dist: scipy>=1.6.0
Requires-Dist: matplotlib>=3.3.0
Requires-Dist: pandas>=1.2.0
Requires-Dist: pygmt>=0.5.0
Dynamic: author
Dynamic: author-email
Dynamic: classifier
Dynamic: description
Dynamic: description-content-type
Dynamic: home-page
Dynamic: project-url
Dynamic: requires-dist
Dynamic: requires-python
Dynamic: summary
